matrixfuncs/__init__.py
matrixfuncs/_farray.py
matrixfuncs/_mspace.py
matrixfuncs/_version.py
matrixfuncs/utils/__init__.py
matrixfuncs/utils/_fcoeffs.py
matrixfuncs/utils/_misc.py
matrixfuncs-0.2.0.dist-info/LICENSE
matrixfuncs-0.2.0.dist-info/METADATA
matrixfuncs-0.2.0.dist-info/WHEEL
matrixfuncs-0.2.0.dist-info/top_level.txt
matrixfuncs-0.2.0.dist-info/RECORD
