Metadata-Version: 2.2
Name: matrixfuncs
Version: 0.2.0
Summary: A package for computing matrix functions using eigenvalue decomposition.
License: LGPL-3.0-only
Project-URL: Github, https://github.com/nextdorf/matrix-functions
Keywords: matrix,linear algebra,eigenvalues,numerical methods
Classifier: Development Status :: 4 - Beta
Classifier: License :: OSI Approved :: GNU Lesser General Public License v3 (LGPLv3)
Classifier: Intended Audience :: Science/Research
Classifier: Programming Language :: Python :: 3
Classifier: Topic :: Scientific/Engineering :: Mathematics
Classifier: Topic :: Scientific/Engineering :: Artificial Intelligence
Requires-Python: >=3.10
License-File: LICENSE
Requires-Dist: numpy
Requires-Dist: scipy
Requires-Dist: numdifftools
